plank/configuration/__init__.py
plank/configuration/builtins/__init__.py
plank/configuration/builtins/app.py
plank/configuration/builtins/extra.py
plank/configuration/builtins/logger.py
plank/configuration/builtins/path.py
plank/configuration/builtins/plugin.py
plank/configuration/builtins/service.py
plank/configuration/info.py
plank/context/__init__.py
plank_material-0.1.0.dist-info/LICENSE
plank_material-0.1.0.dist-info/WHEEL
plank_material-0.1.0.dist-info/METADATA
plank_material-0.1.0.dist-info/RECORD
