Metadata-Version: 2.1
Name: plank-material
Version: 0.1.0
Summary: 
Author: Grady Zhuo
Author-email: grady@ospark.org
Requires-Python: >=3.8,<4.0
Classifier: Programming Language :: Python :: 3
Classifier: Programming Language :: Python :: 3.8
Classifier: Programming Language :: Python :: 3.9
Classifier: Programming Language :: Python :: 3.10
Classifier: Programming Language :: Python :: 3.11
Requires-Dist: plank-core (>=0.1.0,<0.2.0)
Requires-Dist: toml (>=0.10.2,<0.11.0)
